power_text/__init__.py
power_text/local_emoji_source.py
power_text/power_text.py
powertext-0.6.0.dist-info/licenses/LICENSE
powertext-0.6.0.dist-info/licenses/NOTICE
powertext-0.6.0.dist-info/METADATA
powertext-0.6.0.dist-info/WHEEL
powertext-0.6.0.dist-info/top_level.txt
powertext-0.6.0.dist-info/RECORD
