Metadata-Version: 2.4
Name: PowerText
Version: 0.6.0
Summary: PowerText is a text renderer for Pillow that supports emojis, multiple fonts, automatic line wrapping, and automatic text truncation.
Author-email: 校溯 <xiaosu-1009@qq.com>
License:                                  Apache License
Project-URL: Homepage, https://github.com/xiaosuyyds/PowerText/
Keywords: text renderer,emoji,image-processing,pillow
Classifier: Programming Language :: Python :: 3
Classifier: License :: OSI Approved :: Apache Software License
Classifier: Operating System :: OS Independent
Requires-Python: >=3.10
License-File: LICENSE
License-File: NOTICE
Requires-Dist: Pillow>=10.0
Requires-Dist: fonttools>=4.25
Provides-Extra: full
Requires-Dist: emoji~=1.6.3; extra == "full"
Requires-Dist: pilmoji>=2.0; extra == "full"
Dynamic: license-file
